LICENSE
MANIFEST.in
README.md
setup.py
streamlit_disqus_darkmode/__init__.py
streamlit_disqus_darkmode.egg-info/PKG-INFO
streamlit_disqus_darkmode.egg-info/SOURCES.txt
streamlit_disqus_darkmode.egg-info/dependency_links.txt
streamlit_disqus_darkmode.egg-info/requires.txt
streamlit_disqus_darkmode.egg-info/top_level.txt