Metadata-Version: 2.1
Name: streamlit-disqus-darkmode
Version: 0.12
Summary: A streamlit component to embed Disqus in your applications.
Home-page: https://github.com/leonfresh/streamlit-disqus-darkmode
Author: leonfresh
Author-email: 
Requires-Python: >=3.6
License-File: LICENSE
